{
  "Navrangpura_Store": 0,
  "CG_Road_Outlet": 0,
  "Satellite_Branch": 0,
  "Vastrapur_Shop": 0,
  "Bodakdev_Center": 0,
  "Prahlad_Nagar_Store": 0,
  "Maninagar_Outlet": 0,
  "Ghatlodia_Branch": 0,
  "Chandkheda_Store": 0,
  "Motera_Shop": 0,
  "Naroda_Center": 0,
  "Odhav_Outlet": 0,
  "Vatva_Store": 0,
  "Lambha_Branch": 0,
  "Narol_Shop": 0,
  "Isanpur_Store": 0,
  "Nikol_Center": 0,
  "Vastral_Outlet": 0,
  "Rakhial_Branch": 0,
  "Bapunagar_Store": 0,
  "Amraiwadi_Shop": 0,
  "Gomtipur_Center": 0,
  "Khadia_Outlet": 0,
  "Jamalpur_Store": 0,
  "Dariapur_Branch": 0,
  "Mirzapur_Shop": 0,
  "Kalupur_Center": 0,
  "Shahpur_Outlet": 0,
  "Paldi_Store": 0,
  "Ambawadi_Branch": 0,
  "Ellisbridge_Shop": 0,
  "Memnagar_Center": 0,
  "Thaltej_Outlet": 0,
  "Shilaj_Store": 0,
  "Bopal_Branch": 0,
  "Ghuma_Shop": 0,
  "Manipur_Center": 0,
  "Sarkhej_Outlet": 0,
  "Juhapura_Store": 0,
  "Vejalpur_Branch": 0,
  "Jodhpur_Shop": 0,
  "Ambli_Center": 0,
  "Shela_Outlet": 0,
  "Bavla_Store": 0,
  "Sanand_Branch": 0,
  "Vinzol_Shop": 0,
  "Hathijan_Center": 0,
  "Aslali_Outlet": 0,
  "Dholka_Store": 0,
  "Dhandhuka_Branch": 0,
  "Viramgam_Shop": 0,
  "Detroj_Center": 0,
  "Mandal_Outlet": 0,
  "Mumbai_Andheri_Store": 0,
  "Mumbai_Bandra_Store": 0,
  "Mumbai_Dadar_Store": 0,
  "Mumbai_Powai_Store": 0,
  "Mumbai_Borivali_Store": 0,
  "Mumbai_Colaba_Store": 0,
  "Delhi_Connaught_Place_Store": 3,
  "Delhi_Saket_Store": 3,
  "Delhi_Rohini_Store": 3,
  "Delhi_Dwarka_Store": 3,
  "Delhi_Karol_Bagh_Store": 3,
  "Delhi_Lajpat_Nagar_Store": 3,
  "Bengaluru_Indiranagar_Store": 2,
  "Bengaluru_Koramangala_Store": 2,
  "Bengaluru_Whitefield_Store": 2,
  "Bengaluru_Jayanagar_Store": 2,
  "Bengaluru_Hebbal_Store": 2,
  "Bengaluru_Electronic_City_Store": 2,
  "Chennai_T_Nagar_Store": 2,
  "Chennai_Adyar_Store": 2,
  "Chennai_Velachery_Store": 2,
  "Chennai_Anna_Nagar_Store": 2,
  "Chennai_Guindy_Store": 2,
  "Chennai_Mylapore_Store": 2,
  "Hyderabad_Banjara_Hills_Store": 4,
  "Hyderabad_Hitech_City_Store": 4,
  "Hyderabad_Secunderabad_Store": 4,
  "Hyderabad_Gachibowli_Store": 4,
  "Hyderabad_Kukatpally_Store": 4,
  "Hyderabad_Charminar_Store": 4,
  "Kolkata_Park_Street_Store": 1,
  "Kolkata_Salt_Lake_Store": 1,
  "Kolkata_Howrah_Store": 1,
  "Kolkata_New_Town_Store": 1,
  "Kolkata_Ballygunge_Store": 1,
  "Kolkata_Dum_Dum_Store": 1,
  "Pune_Koregaon_Park_Store": 0,
  "Pune_Hinjewadi_Store": 0,
  "Pune_Baner_Store": 0,
  "Pune_Kothrud_Store": 0,
  "Pune_Viman_Nagar_Store": 0,
  "Pune_Hadapsar_Store": 0,
  "Jaipur_C_Scheme_Store": 3,
  "Jaipur_Mansarovar_Store": 3,
  "Jaipur_Malviya_Nagar_Store": 3,
  "Jaipur_Vaishali_Nagar_Store": 3,
  "Jaipur_Tonk_Road_Store": 3,
  "Jaipur_Bani_Park_Store": 3,
  "Surat_Adajan_Store": 0,
  "Surat_Vesu_Store": 0,
  "Surat_Varachha_Store": 0,
  "Surat_Ring_Road_Store": 0,
  "Surat_Katargam_Store": 0,
  "Surat_Udhna_Store": 0,
  "Lucknow_Hazratganj_Store": 3,
  "Lucknow_Gomti_Nagar_Store": 3,
  "Lucknow_Aliganj_Store": 3,
  "Lucknow_Indira_Nagar_Store": 3,
  "Lucknow_Aminabad_Store": 3,
  "Lucknow_Charbagh_Store": 3,
  "Kanpur_Swaroop_Nagar_Store": 3,
  "Kanpur_Kakadeo_Store": 3,
  "Kanpur_Civil_Lines_Store": 3,
  "Kanpur_Kidwai_Nagar_Store": 3,
  "Kanpur_Govind_Nagar_Store": 3,
  "Kanpur_Mall_Road_Store": 3,
  "Nagpur_Sitabuldi_Store": 4,
  "Nagpur_Dharampeth_Store": 4,
  "Nagpur_Mahal_Store": 4,
  "Nagpur_Manish_Nagar_Store": 4,
  "Nagpur_Sadar_Store": 4,
  "Nagpur_Hingna_Store": 4,
  "Indore_Vijay_Nagar_Store": 0,
  "Indore_Palasia_Store": 0,
  "Indore_Rau_Store": 0,
  "Indore_Rajwada_Store": 0,
  "Indore_Bhawarkua_Store": 0,
  "Indore_Scheme_78_Store": 0,
  "Bhopal_MP_Nagar_Store": 0,
  "Bhopal_New_Market_Store": 0,
  "Bhopal_Arera_Colony_Store": 0,
  "Bhopal_Kolar_Road_Store": 0,
  "Bhopal_Bairagarh_Store": 0,
  "Bhopal_Shahpura_Store": 0,
  "Patna_Boring_Road_Store": 1,
  "Patna_Kankarbagh_Store": 1,
  "Patna_Patliputra_Store": 1,
  "Patna_Fraser_Road_Store": 1,
  "Patna_Bailey_Road_Store": 1,
  "Patna_Danapur_Store": 1,
  "Kochi_Edappally_Store": 2,
  "Kochi_Kakkanad_Store": 2,
  "Kochi_Fort_Kochi_Store": 2,
  "Kochi_MG_Road_Store": 2,
  "Kochi_Vyttila_Store": 2,
  "Kochi_Panampilly_Nagar_Store": 2,
  "Coimbatore_RS_Puram_Store": 2,
  "Coimbatore_Gandhipuram_Store": 2,
  "Coimbatore_Peelamedu_Store": 2,
  "Coimbatore_Saibaba_Colony_Store": 2,
  "Coimbatore_Singanallur_Store": 2,
  "Coimbatore_Town_Hall_Store": 2,
  "Visakhapatnam_Dwaraka_Nagar_Store": 4,
  "Visakhapatnam_MVP_Colony_Store": 4,
  "Visakhapatnam_Gajuwaka_Store": 4,
  "Visakhapatnam_Madhurawada_Store": 4,
  "Visakhapatnam_Beach_Road_Store": 4,
  "Visakhapatnam_Akkayyapalem_Store": 4,
  "Chandigarh_Sector_17_Store": 3,
  "Chandigarh_Sector_22_Store": 3,
  "Chandigarh_Sector_35_Store": 3,
  "Chandigarh_Manimajra_Store": 3,
  "Chandigarh_Industrial_Area_Store": 3,
  "Chandigarh_Zirakpur_Store": 3,
  "Guwahati_Paltan_Bazaar_Store": 1,
  "Guwahati_Dispur_Store": 1,
  "Guwahati_Ganeshguri_Store": 1,
  "Guwahati_Beltola_Store": 1,
  "Guwahati_Fancy_Bazaar_Store": 1,
  "Guwahati_Six_Mile_Store": 1
}